psdest/__init__.py
psdest/cpsder.cp37-win_amd64.pyd
psdest/libfftw3-3.dll
psdest/libfftw3f-3.dll
psdest/pypsder.py
psdest-0.1.0.dist-info/LICENCE
psdest-0.1.0.dist-info/METADATA
psdest-0.1.0.dist-info/WHEEL
psdest-0.1.0.dist-info/top_level.txt
psdest-0.1.0.dist-info/RECORD
