Metadata-Version: 2.1
Name: psdest
Version: 0.1.0
Summary: PSD estimation
Home-page: https://gitlab.com/resolvedinstruments/psdest
Author: Callum Doolin
Author-email: callum@resolvedinstruments.com
License: MIT
Classifier: License :: OSI Approved :: MIT License
Classifier: Programming Language :: Python :: 3.6
Classifier: Programming Language :: Python :: 3.7
Classifier: Programming Language :: Python :: 3.8
Classifier: Programming Language :: Python :: 3.9
Classifier: Programming Language :: Python :: 3.10
Classifier: Environment :: Win32 (MS Windows)
Classifier: Operating System :: POSIX :: Linux
Classifier: Operating System :: Microsoft :: Windows
Classifier: Topic :: Scientific/Engineering
Requires-Python: >=3.6
License-File: LICENCE
Requires-Dist: numpy
Requires-Dist: scipy
